dmel/__init__.py
dmel/dmel.py
dmel/utils.py
dmel-1.0.1.dist-info/licenses/LICENSE
dmel-1.0.1.dist-info/WHEEL
dmel-1.0.1.dist-info/METADATA
dmel-1.0.1.dist-info/RECORD
