Metadata-Version: 2.4
Name: dmel
Version: 1.0.1
Summary: A python package for dmel log mel-filterbanks discretization.
Author: Apple
Requires-Python: >3.8
License-File: LICENSE
Requires-Dist: librosa
Requires-Dist: torch
Requires-Dist: einops
Requires-Dist: pytest ; extra == "dev"
Requires-Dist: pytest-cov ; extra == "dev"
Requires-Dist: pre-commit ; extra == "dev"
Provides-Extra: dev
